{
    "sourceFile": "Frontend/angular.json",
    "activeCommit": 0,
    "commits": [
        {
            "activePatchIndex": 3,
            "patches": [
                {
                    "date": 1748188894017,
                    "content": "Index: \n===================================================================\n--- \n+++ \n"
                },
                {
                    "date": 1748190280575,
                    "content": "Index: \n===================================================================\n--- \n+++ \n@@ -1,120 +1,37 @@\n-{\r\n-  \"$schema\": \"./node_modules/@angular/cli/lib/config/schema.json\",\r\n-  \"cli\": {\r\n-    \"analytics\": false\r\n-  },\r\n-  \"version\": 1,\r\n-  \"newProjectRoot\": \"projects\",\r\n-  \"projects\": {\r\n-    \"coreui-free-angular-admin-template\": {\r\n-      \"projectType\": \"application\",\r\n-      \"schematics\": {\r\n-        \"@schematics/angular:component\": {\r\n-          \"style\": \"scss\"\r\n-        },\r\n-        \"@schematics/angular:application\": {\r\n-          \"strict\": true\r\n-        }\r\n-      },\r\n-      \"root\": \"\",\r\n-      \"sourceRoot\": \"src\",\r\n-      \"prefix\": \"app\",\r\n-      \"architect\": {\r\n-        \"build\": {\r\n-          \"builder\": \"@angular-devkit/build-angular:application\",\r\n-          \"options\": {\r\n-            \"outputPath\": \"dist/browser\",\r\n-            \"index\": \"src/index.html\",\r\n-            \"browser\": \"src/main.ts\",\r\n-            \"polyfills\": [\r\n-              \"@angular/localize/init\",\r\n-              \"zone.js\"\r\n-            ],\r\n-            \"tsConfig\": \"tsconfig.app.json\",\r\n-            \"inlineStyleLanguage\": \"scss\",\r\n-            \"preserveSymlinks\": true,\r\n-            \"assets\": [\r\n-              \"src/favicon.ico\",\r\n-              \"src/assets\"\r\n-            ],\r\n-            \"styles\": [\r\n-              \"src/scss/styles.scss\"\r\n-            ],\r\n-            \"scripts\": [],\r\n-            \"allowedCommonJsDependencies\": [],\r\n-            \"stylePreprocessorOptions\": {\r\n-              \"sass\": {\r\n-                \"silenceDeprecations\": []\r\n-              }\r\n-            }\r\n-          },\r\n-          \"configurations\": {\r\n-            \"production\": {\r\n-              \"budgets\": [\r\n-                {\r\n-                  \"type\": \"initial\",\r\n-                  \"maximumWarning\": \"6mb\",\r\n-                  \"maximumError\": \"7mb\"\r\n-                },\r\n-                {\r\n-                  \"type\": \"anyComponentStyle\",\r\n-                  \"maximumWarning\": \"2kb\",\r\n-                  \"maximumError\": \"4kb\"\r\n-                }\r\n-              ],\r\n-              \"outputHashing\": \"all\"\r\n-            },\r\n-            \"development\": {\r\n-              \"optimization\": false,\r\n-              \"extractLicenses\": false,\r\n-              \"sourceMap\": true,\r\n-              \"namedChunks\": true\r\n-            }\r\n-          },\r\n-          \"defaultConfiguration\": \"production\"\r\n-        },\r\n-        \"serve\": {\r\n-          \"builder\": \"@angular-devkit/build-angular:dev-server\",\r\n-          \"configurations\": {\r\n-            \"production\": {\r\n-              \"buildTarget\": \"coreui-free-angular-admin-template:build:production\"\r\n-            },\r\n-            \"development\": {\r\n-              \"buildTarget\": \"coreui-free-angular-admin-template:build:development\"\r\n-            }\r\n-          },\r\n-          \"defaultConfiguration\": \"development\"\r\n-        },\r\n-        \"extract-i18n\": {\r\n-          \"builder\": \"@angular-devkit/build-angular:extract-i18n\",\r\n-          \"options\": {\r\n-            \"buildTarget\": \"coreui-free-angular-admin-template:build\"\r\n-          }\r\n-        },\r\n-        \"test\": {\r\n-          \"builder\": \"@angular-devkit/build-angular:karma\",\r\n-          \"options\": {\r\n-            \"polyfills\": [\r\n-              \"zone.js\",\r\n-              \"zone.js/testing\"\r\n-            ],\r\n-            \"tsConfig\": \"tsconfig.spec.json\",\r\n-            \"karmaConfig\": \"karma.conf.js\",\r\n-            \"inlineStyleLanguage\": \"scss\",\r\n-            \"assets\": [\r\n-              \"src/favicon.ico\",\r\n-              \"src/assets\"\r\n-            ],\r\n-            \"styles\": [\r\n-              \"src/scss/styles.scss\"\r\n-            ],\r\n-            \"scripts\": []\r\n-          }\r\n-        },\r\n-        \"deploy\": {\r\n-          \"builder\": \"angular-cli-ghpages:deploy\"\r\n-        }\r\n-      }\r\n-    }\r\n-  }\r\n-}\r\n+name: Deploy to GitHub Pages\r\n+\r\n+on:\r\n+  push:\r\n+    branches: [ thausif, main ] \r\n+  workflow_dispatch:\r\n+\r\n+jobs:\r\n+  build-and-deploy:\r\n+    runs-on: ubuntu-latest\r\n+    steps:\r\n+      - name: Checkout\r\n+        uses: actions/checkout@v3\r\n+\r\n+      - name: Set up Node.js\r\n+        uses: actions/setup-node@v3\r\n+        with:\r\n+          node-version: '20'\r\n+          cache: 'npm'\r\n+          cache-dependency-path: 'Frontend/package-lock.json'\r\n+\r\n+      - name: Install dependencies\r\n+        working-directory: ./Frontend\r\n+        run: npm ci\r\n+\r\n+      - name: Build\r\n+        working-directory: ./Frontend\r\n+        run: npm run build -- --configuration production --base-href=/AdvSoftTech-Assignment/\r\n+\r\n+      # Simplified deployment that works with the correct output path\r\n+      - name: Deploy to GitHub Pages\r\n+        uses: JamesIves/github-pages-deploy-action@v4\r\n+        with:\r\n+          folder: Frontend/dist/coreui-free-angular-admin-template\r\n+          branch: gh-pages\r\n+          token: ${{ secrets.DEPLOY_TOKEN }}  # Use the custom token\r\n+          clean: true\n\\ No newline at end of file\n"
                },
                {
                    "date": 1748190892788,
                    "content": "Index: \n===================================================================\n--- \n+++ \n@@ -1,37 +1,75 @@\n name: Deploy to GitHub Pages\r\n \r\n on:\r\n   push:\r\n-    branches: [ thausif, main ] \r\n+    branches:\r\n+      - main\r\n+      - thausif\r\n+  # Allow manual triggering\r\n   workflow_dispatch:\r\n \r\n+# Add permissions block\r\n+permissions:\r\n+  contents: write\r\n+\r\n jobs:\r\n   build-and-deploy:\r\n     runs-on: ubuntu-latest\r\n     steps:\r\n-      - name: Checkout\r\n-        uses: actions/checkout@v3\r\n+      - name: Checkout code\r\n+        uses: actions/checkout@v4\r\n \r\n-      - name: Set up Node.js\r\n-        uses: actions/setup-node@v3\r\n+      - name: Setup Node.js\r\n+        uses: actions/setup-node@v4\r\n         with:\r\n-          node-version: '20'\r\n+          node-version: 20\r\n           cache: 'npm'\r\n-          cache-dependency-path: 'Frontend/package-lock.json'\r\n+          cache-dependency-path: './Frontend/package-lock.json'\r\n \r\n       - name: Install dependencies\r\n-        working-directory: ./Frontend\r\n-        run: npm ci\r\n+        run: |\r\n+          cd Frontend\r\n+          npm ci --legacy-peer-deps\r\n \r\n-      - name: Build\r\n-        working-directory: ./Frontend\r\n-        run: npm run build -- --configuration production --base-href=/AdvSoftTech-Assignment/\r\n+      - name: Update base URL for GitHub Pages\r\n+        run: |\r\n+          cd Frontend\r\n+          sed -i 's/<base href=\"\\/\">/<base href=\"\\/AdvSoftTech-Assignment\\/\">/' src/index.html\r\n+      \r\n+      - name: Build Angular project\r\n+        run: |\r\n+          cd Frontend\r\n+          npm run build -- --configuration production --base-href=/AdvSoftTech-Assignment/ --legacy-peer-deps\r\n \r\n-      # Simplified deployment that works with the correct output path\r\n+      - name: Debug directory structure\r\n+        run: |\r\n+          find Frontend/dist -type d | sort\r\n+          find Frontend/dist -name \"index.html\" -type f\r\n+\r\n+      # Fix the variable capture so it's available for the deploy step\r\n+      - name: Add routing files and set output\r\n+        id: find-output\r\n+        run: |\r\n+          # Find the directory containing index.html\r\n+          INDEX_DIR=$(find Frontend/dist -name \"index.html\" -type f | xargs dirname)\r\n+          if [ -n \"$INDEX_DIR\" ]; then\r\n+            echo \"Found index.html in $INDEX_DIR\"\r\n+            cd \"$INDEX_DIR\"\r\n+            \r\n+            # Create necessary files for GitHub Pages\r\n+            echo \"/* /index.html 200\" > _redirects\r\n+            cp index.html 404.html\r\n+            touch .nojekyll\r\n+            \r\n+            echo \"output_dir=$INDEX_DIR\" >> $GITHUB_OUTPUT\r\n+          else\r\n+            echo \"Error: Could not find index.html in build output\"\r\n+            exit 1\r\n+          fi\r\n+\r\n       - name: Deploy to GitHub Pages\r\n         uses: JamesIves/github-pages-deploy-action@v4\r\n         with:\r\n-          folder: Frontend/dist/coreui-free-angular-admin-template\r\n+          folder: ${{ steps.find-output.outputs.output_dir || 'Frontend/dist/coreui-free-angular-admin-template' }}\r\n           branch: gh-pages\r\n-          token: ${{ secrets.DEPLOY_TOKEN }}  # Use the custom token\r\n           clean: true\n\\ No newline at end of file\n"
                },
                {
                    "date": 1748190899356,
                    "content": "Index: \n===================================================================\n--- \n+++ \n@@ -1,75 +1,117 @@\n-name: Deploy to GitHub Pages\r\n-\r\n-on:\r\n-  push:\r\n-    branches:\r\n-      - main\r\n-      - thausif\r\n-  # Allow manual triggering\r\n-  workflow_dispatch:\r\n-\r\n-# Add permissions block\r\n-permissions:\r\n-  contents: write\r\n-\r\n-jobs:\r\n-  build-and-deploy:\r\n-    runs-on: ubuntu-latest\r\n-    steps:\r\n-      - name: Checkout code\r\n-        uses: actions/checkout@v4\r\n-\r\n-      - name: Setup Node.js\r\n-        uses: actions/setup-node@v4\r\n-        with:\r\n-          node-version: 20\r\n-          cache: 'npm'\r\n-          cache-dependency-path: './Frontend/package-lock.json'\r\n-\r\n-      - name: Install dependencies\r\n-        run: |\r\n-          cd Frontend\r\n-          npm ci --legacy-peer-deps\r\n-\r\n-      - name: Update base URL for GitHub Pages\r\n-        run: |\r\n-          cd Frontend\r\n-          sed -i 's/<base href=\"\\/\">/<base href=\"\\/AdvSoftTech-Assignment\\/\">/' src/index.html\r\n-      \r\n-      - name: Build Angular project\r\n-        run: |\r\n-          cd Frontend\r\n-          npm run build -- --configuration production --base-href=/AdvSoftTech-Assignment/ --legacy-peer-deps\r\n-\r\n-      - name: Debug directory structure\r\n-        run: |\r\n-          find Frontend/dist -type d | sort\r\n-          find Frontend/dist -name \"index.html\" -type f\r\n-\r\n-      # Fix the variable capture so it's available for the deploy step\r\n-      - name: Add routing files and set output\r\n-        id: find-output\r\n-        run: |\r\n-          # Find the directory containing index.html\r\n-          INDEX_DIR=$(find Frontend/dist -name \"index.html\" -type f | xargs dirname)\r\n-          if [ -n \"$INDEX_DIR\" ]; then\r\n-            echo \"Found index.html in $INDEX_DIR\"\r\n-            cd \"$INDEX_DIR\"\r\n-            \r\n-            # Create necessary files for GitHub Pages\r\n-            echo \"/* /index.html 200\" > _redirects\r\n-            cp index.html 404.html\r\n-            touch .nojekyll\r\n-            \r\n-            echo \"output_dir=$INDEX_DIR\" >> $GITHUB_OUTPUT\r\n-          else\r\n-            echo \"Error: Could not find index.html in build output\"\r\n-            exit 1\r\n-          fi\r\n-\r\n-      - name: Deploy to GitHub Pages\r\n-        uses: JamesIves/github-pages-deploy-action@v4\r\n-        with:\r\n-          folder: ${{ steps.find-output.outputs.output_dir || 'Frontend/dist/coreui-free-angular-admin-template' }}\r\n-          branch: gh-pages\r\n-          clean: true\n\\ No newline at end of file\n+{\r\n+  \"$schema\": \"./node_modules/@angular/cli/lib/config/schema.json\",\r\n+  \"cli\": {\r\n+    \"analytics\": false\r\n+  },\r\n+  \"version\": 1,\r\n+  \"newProjectRoot\": \"projects\",\r\n+  \"projects\": {\r\n+    \"coreui-free-angular-admin-template\": {\r\n+      \"projectType\": \"application\",\r\n+      \"schematics\": {\r\n+        \"@schematics/angular:component\": {\r\n+          \"style\": \"scss\"\r\n+        },\r\n+        \"@schematics/angular:application\": {\r\n+          \"strict\": true\r\n+        }\r\n+      },\r\n+      \"root\": \"\",\r\n+      \"sourceRoot\": \"src\",\r\n+      \"prefix\": \"app\",\r\n+      \"architect\": {\r\n+        \"build\": {\r\n+          \"builder\": \"@angular-devkit/build-angular:application\",\r\n+          \"options\": {\r\n+            \"outputPath\": \"dist/coreui-free-angular-admin-template\",\r\n+            \"index\": \"src/index.html\",\r\n+            \"browser\": \"src/main.ts\",\r\n+            \"polyfills\": [\r\n+              \"@angular/localize/init\",\r\n+              \"zone.js\"\r\n+            ],\r\n+            \"tsConfig\": \"tsconfig.app.json\",\r\n+            \"inlineStyleLanguage\": \"scss\",\r\n+            \"preserveSymlinks\": true,\r\n+            \"assets\": [\r\n+              \"src/favicon.ico\",\r\n+              \"src/assets\"\r\n+            ],\r\n+            \"styles\": [\r\n+              \"src/scss/styles.scss\"\r\n+            ],\r\n+            \"scripts\": [],\r\n+            \"allowedCommonJsDependencies\": [],\r\n+            \"stylePreprocessorOptions\": {\r\n+              \"sass\": {\r\n+                \"silenceDeprecations\": []\r\n+              }\r\n+            }\r\n+          },\r\n+          \"configurations\": {\r\n+            \"production\": {\r\n+              \"budgets\": [\r\n+                {\r\n+                  \"type\": \"initial\",\r\n+                  \"maximumWarning\": \"6mb\",\r\n+                  \"maximumError\": \"7mb\"\r\n+                },\r\n+                {\r\n+                  \"type\": \"anyComponentStyle\",\r\n+                  \"maximumWarning\": \"2kb\",\r\n+                  \"maximumError\": \"4kb\"\r\n+                }\r\n+              ],\r\n+              \"outputHashing\": \"all\"\r\n+            },\r\n+            \"development\": {\r\n+              \"optimization\": false,\r\n+              \"extractLicenses\": false,\r\n+              \"sourceMap\": true,\r\n+              \"namedChunks\": true\r\n+            }\r\n+          },\r\n+          \"defaultConfiguration\": \"production\"\r\n+        },\r\n+        \"serve\": {\r\n+          \"builder\": \"@angular-devkit/build-angular:dev-server\",\r\n+          \"configurations\": {\r\n+            \"production\": {\r\n+              \"buildTarget\": \"coreui-free-angular-admin-template:build:production\"\r\n+            },\r\n+            \"development\": {\r\n+              \"buildTarget\": \"coreui-free-angular-admin-template:build:development\"\r\n+            }\r\n+          },\r\n+          \"defaultConfiguration\": \"development\"\r\n+        },\r\n+        \"extract-i18n\": {\r\n+          \"builder\": \"@angular-devkit/build-angular:extract-i18n\",\r\n+          \"options\": {\r\n+            \"buildTarget\": \"coreui-free-angular-admin-template:build\"\r\n+          }\r\n+        },\r\n+        \"test\": {\r\n+          \"builder\": \"@angular-devkit/build-angular:karma\",\r\n+          \"options\": {\r\n+            \"polyfills\": [\r\n+              \"zone.js\",\r\n+              \"zone.js/testing\"\r\n+            ],\r\n+            \"tsConfig\": \"tsconfig.spec.json\",\r\n+            \"karmaConfig\": \"karma.conf.js\",\r\n+            \"inlineStyleLanguage\": \"scss\",\r\n+            \"assets\": [\r\n+              \"src/favicon.ico\",\r\n+              \"src/assets\"\r\n+            ],\r\n+            \"styles\": [\r\n+              \"src/scss/styles.scss\"\r\n+            ],\r\n+            \"scripts\": []\r\n+          }\r\n+        }\r\n+      }\r\n+    }\r\n+  }\r\n+}\r\n"
                }
            ],
            "date": 1748188894017,
            "name": "Commit-0",
            "content": "{\r\n  \"$schema\": \"./node_modules/@angular/cli/lib/config/schema.json\",\r\n  \"cli\": {\r\n    \"analytics\": false\r\n  },\r\n  \"version\": 1,\r\n  \"newProjectRoot\": \"projects\",\r\n  \"projects\": {\r\n    \"coreui-free-angular-admin-template\": {\r\n      \"projectType\": \"application\",\r\n      \"schematics\": {\r\n        \"@schematics/angular:component\": {\r\n          \"style\": \"scss\"\r\n        },\r\n        \"@schematics/angular:application\": {\r\n          \"strict\": true\r\n        }\r\n      },\r\n      \"root\": \"\",\r\n      \"sourceRoot\": \"src\",\r\n      \"prefix\": \"app\",\r\n      \"architect\": {\r\n        \"build\": {\r\n          \"builder\": \"@angular-devkit/build-angular:application\",\r\n          \"options\": {\r\n            \"outputPath\": \"dist/browser\",\r\n            \"index\": \"src/index.html\",\r\n            \"browser\": \"src/main.ts\",\r\n            \"polyfills\": [\r\n              \"@angular/localize/init\",\r\n              \"zone.js\"\r\n            ],\r\n            \"tsConfig\": \"tsconfig.app.json\",\r\n            \"inlineStyleLanguage\": \"scss\",\r\n            \"preserveSymlinks\": true,\r\n            \"assets\": [\r\n              \"src/favicon.ico\",\r\n              \"src/assets\"\r\n            ],\r\n            \"styles\": [\r\n              \"src/scss/styles.scss\"\r\n            ],\r\n            \"scripts\": [],\r\n            \"allowedCommonJsDependencies\": [],\r\n            \"stylePreprocessorOptions\": {\r\n              \"sass\": {\r\n                \"silenceDeprecations\": []\r\n              }\r\n            }\r\n          },\r\n          \"configurations\": {\r\n            \"production\": {\r\n              \"budgets\": [\r\n                {\r\n                  \"type\": \"initial\",\r\n                  \"maximumWarning\": \"6mb\",\r\n                  \"maximumError\": \"7mb\"\r\n                },\r\n                {\r\n                  \"type\": \"anyComponentStyle\",\r\n                  \"maximumWarning\": \"2kb\",\r\n                  \"maximumError\": \"4kb\"\r\n                }\r\n              ],\r\n              \"outputHashing\": \"all\"\r\n            },\r\n            \"development\": {\r\n              \"optimization\": false,\r\n              \"extractLicenses\": false,\r\n              \"sourceMap\": true,\r\n              \"namedChunks\": true\r\n            }\r\n          },\r\n          \"defaultConfiguration\": \"production\"\r\n        },\r\n        \"serve\": {\r\n          \"builder\": \"@angular-devkit/build-angular:dev-server\",\r\n          \"configurations\": {\r\n            \"production\": {\r\n              \"buildTarget\": \"coreui-free-angular-admin-template:build:production\"\r\n            },\r\n            \"development\": {\r\n              \"buildTarget\": \"coreui-free-angular-admin-template:build:development\"\r\n            }\r\n          },\r\n          \"defaultConfiguration\": \"development\"\r\n        },\r\n        \"extract-i18n\": {\r\n          \"builder\": \"@angular-devkit/build-angular:extract-i18n\",\r\n          \"options\": {\r\n            \"buildTarget\": \"coreui-free-angular-admin-template:build\"\r\n          }\r\n        },\r\n        \"test\": {\r\n          \"builder\": \"@angular-devkit/build-angular:karma\",\r\n          \"options\": {\r\n            \"polyfills\": [\r\n              \"zone.js\",\r\n              \"zone.js/testing\"\r\n            ],\r\n            \"tsConfig\": \"tsconfig.spec.json\",\r\n            \"karmaConfig\": \"karma.conf.js\",\r\n            \"inlineStyleLanguage\": \"scss\",\r\n            \"assets\": [\r\n              \"src/favicon.ico\",\r\n              \"src/assets\"\r\n            ],\r\n            \"styles\": [\r\n              \"src/scss/styles.scss\"\r\n            ],\r\n            \"scripts\": []\r\n          }\r\n        },\r\n        \"deploy\": {\r\n          \"builder\": \"angular-cli-ghpages:deploy\"\r\n        }\r\n      }\r\n    }\r\n  }\r\n}\r\n"
        }
    ]
}